LICENSE
MANIFEST.in
README.rst
ZENOSS-PROCESS-MIB.txt
setup.py
zenoss_snmp_module.py
zenoss_snmp_module.egg-info/PKG-INFO
zenoss_snmp_module.egg-info/SOURCES.txt
zenoss_snmp_module.egg-info/dependency_links.txt
zenoss_snmp_module.egg-info/entry_points.txt
zenoss_snmp_module.egg-info/requires.txt
zenoss_snmp_module.egg-info/test_info.txt
zenoss_snmp_module.egg-info/top_level.txt