Metadata-Version: 1.0
Name: zenoss-snmp-module
Version: 1.0.0rc4
Summary: Net-SNMP pass_persist script for monitoring Zenoss.
Home-page: http://github.com/cluther/zenoss-snmp-module
Author: Chet Luther
Author-email: chet.luther@gmail.com
License: GPLv2
Keywords: zenoss snmp net-snmp
Platform: UNKNOWN
Classifier: Development Status :: 3 - Alpha
Classifier: Environment :: Other Environment
Classifier: Intended Audience :: System Administrators
Classifier: License :: OSI Approved :: GNU General Public License v2 or later (GPLv2+)
Classifier: Natural Language :: English
Classifier: Operating System :: POSIX :: Linux
Classifier: Programming Language :: Python :: 2
Classifier: Topic :: System :: Monitoring
